package com.qualcomm.ftccommon;

import android.content.Context;
import android.os.Bundle;
import android.view.LayoutInflater;
import android.view.View;
import android.widget.Button;
import android.widget.FrameLayout;
import android.widget.LinearLayout;
import android.widget.RadioButton;
import android.widget.RadioGroup;
import android.widget.TextView;
import com.qualcomm.robotcore.exception.RobotCoreException;
import com.qualcomm.robotcore.hardware.USBAccessibleLynxModule;
import com.qualcomm.robotcore.robocol.Command;
import com.qualcomm.robotcore.util.ReadWriteFile;
import com.qualcomm.robotcore.util.RobotLog;
import com.qualcomm.robotcore.util.ThreadPool;
import java.io.File;
import java.util.ArrayList;
import java.util.Collections;
import java.util.Comparator;
import java.util.HashMap;
import java.util.Iterator;
import java.util.List;
import java.util.Map;
import java.util.UUID;
import java.util.concurrent.ArrayBlockingQueue;
import java.util.concurrent.BlockingQueue;
import java.util.concurrent.TimeUnit;
import org.firstinspires.ftc.robotcore.internal.collections.MutableReference;
import org.firstinspires.ftc.robotcore.internal.collections.SimpleGson;
import org.firstinspires.ftc.robotcore.internal.network.CallbackResult;
import org.firstinspires.ftc.robotcore.internal.network.NetworkConnectionHandler;
import org.firstinspires.ftc.robotcore.internal.network.RecvLoopRunnable;
import org.firstinspires.ftc.robotcore.internal.network.RobotCoreCommandList;
import org.firstinspires.ftc.robotcore.internal.stellaris.FlashLoaderManager;
import org.firstinspires.ftc.robotcore.internal.system.AppUtil;
import org.firstinspires.ftc.robotcore.internal.system.Deadline;
import org.firstinspires.ftc.robotcore.internal.ui.ThemedActivity;
import org.firstinspires.ftc.robotcore.internal.ui.UILocation;
import org.firstinspires.inspection.R;

public class FtcLynxFirmwareUpdateActivity extends ThemedActivity {
  public static final String TAG = "FtcLynxFirmwareUpdateActivity";
  
  protected BlockingQueue<RobotCoreCommandList.LynxFirmwareUpdateResp> availableFWUpdateResps = new ArrayBlockingQueue<RobotCoreCommandList.LynxFirmwareUpdateResp>(1);
  
  protected BlockingQueue<RobotCoreCommandList.LynxFirmwareImagesResp> availableLynxImages = new ArrayBlockingQueue<RobotCoreCommandList.LynxFirmwareImagesResp>(1);
  
  protected BlockingQueue<RobotCoreCommandList.USBAccessibleLynxModulesResp> availableLynxModules = new ArrayBlockingQueue<RobotCoreCommandList.USBAccessibleLynxModulesResp>(1);
  
  protected boolean cancelUpdate = false;
  
  protected boolean enableUpdateButton = true;
  
  protected RobotCoreCommandList.FWImage firmwareImageFile = new RobotCoreCommandList.FWImage(new File(""), false);
  
  protected Map<View, RobotCoreCommandList.FWImage> firmwareImagesMap = new HashMap<View, RobotCoreCommandList.FWImage>();
  
  protected List<USBAccessibleLynxModule> modulesToUpdate = new ArrayList<USBAccessibleLynxModule>();
  
  protected int msResponseWait = 5000;
  
  protected NetworkConnectionHandler networkConnectionHandler = NetworkConnectionHandler.getInstance();
  
  protected final String originatorId = UUID.randomUUID().toString();
  
  protected RecvLoopRunnable.RecvLoopCallback recvLoopCallback = (RecvLoopRunnable.RecvLoopCallback)new ReceiveLoopCallback(this.originatorId);
  
  protected boolean remoteConfigure = AppUtil.getInstance().isDriverStation();
  
  protected View.OnClickListener updateFileClickListener = new View.OnClickListener() {
      public void onClick(View param1View) {
        FtcLynxFirmwareUpdateActivity ftcLynxFirmwareUpdateActivity = FtcLynxFirmwareUpdateActivity.this;
        ftcLynxFirmwareUpdateActivity.firmwareImageFile = ftcLynxFirmwareUpdateActivity.firmwareImagesMap.get(param1View);
      }
    };
  
  public static void initializeDirectories() {
    AppUtil.getInstance().ensureDirectoryExists(AppUtil.LYNX_FIRMWARE_UPDATE_DIR);
    String str = AppUtil.getDefContext().getString(R.string.lynxFirmwareUpdateReadme);
    ReadWriteFile.writeFile(AppUtil.LYNX_FIRMWARE_UPDATE_DIR, "readme.txt", str);
    str = AppUtil.getDefContext().getString(R.string.robotControllerAppUpdateReadme);
    ReadWriteFile.writeFile(AppUtil.RC_APP_UPDATE_DIR, "readme.txt", str);
  }
  
  protected <T> T awaitResponse(BlockingQueue<T> paramBlockingQueue, T paramT) {
    return awaitResponse(paramBlockingQueue, paramT, this.msResponseWait, TimeUnit.MILLISECONDS, new MutableReference(FwResponseStatus.Succeeded));
  }
  
  protected <T> T awaitResponse(BlockingQueue<T> paramBlockingQueue, T paramT, long paramLong, TimeUnit paramTimeUnit, MutableReference<FwResponseStatus> paramMutableReference) {
    try {
      Deadline deadline = new Deadline(paramLong, paramTimeUnit);
      paramMutableReference.setValue(FwResponseStatus.TimedOut);
      while (!deadline.hasExpired()) {
        T t = paramBlockingQueue.poll(100L, TimeUnit.MILLISECONDS);
        if (t != null) {
          paramMutableReference.setValue(FwResponseStatus.Succeeded);
          return t;
        } 
        if (this.cancelUpdate) {
          paramMutableReference.setValue(FwResponseStatus.Cancelled);
          return paramT;
        } 
      } 
    } catch (InterruptedException interruptedException) {
      Thread.currentThread().interrupt();
    } 
    return paramT;
  }
  
  protected FrameLayout getBackBar() {
    return (FrameLayout)findViewById(R.id.backbar);
  }
  
  protected RobotCoreCommandList.LynxFirmwareImagesResp getCandidateLynxFirmwareImages() {
    RobotCoreCommandList.LynxFirmwareImagesResp lynxFirmwareImagesResp = new RobotCoreCommandList.LynxFirmwareImagesResp();
    this.availableLynxImages.clear();
    sendOrInject(new Command("CMD_GET_CANDIDATE_LYNX_FIRMWARE_IMAGES"));
    lynxFirmwareImagesResp = awaitResponse(this.availableLynxImages, lynxFirmwareImagesResp);
    RobotLog.vv("FtcLynxFirmwareUpdateActivity", "found %d lynx firmware images", new Object[] { Integer.valueOf(lynxFirmwareImagesResp.firmwareImages.size()) });
    return lynxFirmwareImagesResp;
  }
  
  protected List<USBAccessibleLynxModule> getLynxModulesForFirmwareUpdate() {
    RobotCoreCommandList.USBAccessibleLynxModulesRequest uSBAccessibleLynxModulesRequest = new RobotCoreCommandList.USBAccessibleLynxModulesRequest();
    RobotCoreCommandList.USBAccessibleLynxModulesResp uSBAccessibleLynxModulesResp2 = new RobotCoreCommandList.USBAccessibleLynxModulesResp();
    this.availableLynxModules.clear();
    uSBAccessibleLynxModulesRequest.forFirmwareUpdate = true;
    sendOrInject(new Command("CMD_GET_USB_ACCESSIBLE_LYNX_MODULES", uSBAccessibleLynxModulesRequest.serialize()));
    RobotCoreCommandList.USBAccessibleLynxModulesResp uSBAccessibleLynxModulesResp1 = awaitResponse(this.availableLynxModules, uSBAccessibleLynxModulesResp2);
    RobotLog.vv("FtcLynxFirmwareUpdateActivity", "found %d lynx modules", new Object[] { Integer.valueOf(uSBAccessibleLynxModulesResp1.modules.size()) });
    return uSBAccessibleLynxModulesResp1.modules;
  }
  
  public String getTag() {
    return "FtcLynxFirmwareUpdateActivity";
  }
  
  protected void onCreate(Bundle paramBundle) {
    super.onCreate(paramBundle);
    setContentView(R.layout.activity_ftc_lynx_fw_update);
    this.networkConnectionHandler.pushReceiveLoopCallback(this.recvLoopCallback);
  }
  
  protected void onDestroy() {
    super.onDestroy();
    this.networkConnectionHandler.removeReceiveLoopCallback(this.recvLoopCallback);
  }
  
  protected void onPause() {
    super.onPause();
    this.cancelUpdate = true;
  }
  
  protected void onStart() {
    File file;
    super.onStart();
    TextView textView1 = (TextView)findViewById(R.id.lynxFirmwareFilesHeader);
    RadioGroup radioGroup = (RadioGroup)findViewById(R.id.lynxFirmwareAvailableFilesGroup);
    TextView textView2 = (TextView)findViewById(R.id.lynxFirmwareHubsHeader);
    LinearLayout linearLayout = (LinearLayout)findViewById(R.id.lynxFirmwareModuleList);
    TextView textView3 = (TextView)findViewById(R.id.lynxFirmwareInstructionsPost);
    Button button = (Button)findViewById(R.id.lynxFirmwareUpdateButton);
    RobotCoreCommandList.LynxFirmwareImagesResp lynxFirmwareImagesResp = getCandidateLynxFirmwareImages();
    if (lynxFirmwareImagesResp.firmwareImages.isEmpty()) {
      file = AppUtil.getInstance().getRelativePath(lynxFirmwareImagesResp.firstFolder.getParentFile(), AppUtil.LYNX_FIRMWARE_UPDATE_DIR);
      textView2.setText(getString(R.string.lynx_fw_instructions_no_binary, new Object[] { file }));
      textView1.setVisibility(8);
      radioGroup.setVisibility(8);
      linearLayout.setVisibility(8);
      textView3.setVisibility(8);
      button.setEnabled(false);
      return;
    } 
    Collections.sort(((RobotCoreCommandList.LynxFirmwareImagesResp)file).firmwareImages, new Comparator<RobotCoreCommandList.FWImage>() {
          public int compare(RobotCoreCommandList.FWImage param1FWImage1, RobotCoreCommandList.FWImage param1FWImage2) {
            return -param1FWImage1.getName().compareTo(param1FWImage2.getName());
          }
        });
    radioGroup.removeAllViews();
    this.firmwareImagesMap.clear();
    Iterator<RobotCoreCommandList.FWImage> iterator = ((RobotCoreCommandList.LynxFirmwareImagesResp)file).firmwareImages.iterator();
    boolean bool = true;
    while (iterator.hasNext()) {
      RobotCoreCommandList.FWImage fWImage = iterator.next();
      RadioButton radioButton = new RadioButton((Context)this);
      String str2 = fWImage.getName();
      String str1 = str2;
      if (fWImage.isAsset) {
        StringBuilder stringBuilder = new StringBuilder();
        stringBuilder.append(str2);
        stringBuilder.append(" (bundled)");
        str1 = stringBuilder.toString();
      } 
      radioButton.setText(str1);
      radioButton.setOnClickListener(this.updateFileClickListener);
      radioGroup.addView((View)radioButton);
      this.firmwareImagesMap.put(radioButton, fWImage);
      if (bool) {
        this.firmwareImageFile = fWImage;
        radioButton.toggle();
        bool = false;
      } 
    } 
    List<USBAccessibleLynxModule> list = getLynxModulesForFirmwareUpdate();
    this.modulesToUpdate = list;
    if (list.isEmpty()) {
      textView2.setText(R.string.lynx_fw_instructions_no_devices);
      linearLayout.setVisibility(8);
      textView3.setVisibility(8);
      button.setEnabled(false);
      return;
    } 
    textView2.setText(R.string.lynx_fw_instructions_update);
    for (USBAccessibleLynxModule uSBAccessibleLynxModule : this.modulesToUpdate) {
      String str1;
      String str2;
      if (uSBAccessibleLynxModule.getSerialNumber().isEmbedded()) {
        str1 = AppUtil.getDefContext().getString(R.string.lynx_fw_instructions_controlhub_item_title);
      } else {
        str1 = AppUtil.getDefContext().getString(R.string.lynx_fw_instructions_exhub_item_title);
      } 
      String str3 = getString(R.string.lynx_fw_instructions_serial, new Object[] { uSBAccessibleLynxModule.getSerialNumber() });
      if (uSBAccessibleLynxModule.getModuleAddress() == 0) {
        str2 = getString(R.string.lynx_fw_instructions_module_address_unavailable);
      } else {
        str2 = getString(R.string.lynx_fw_instructions_module_address, new Object[] { Integer.valueOf(uSBAccessibleLynxModule.getModuleAddress()) });
      } 
      String str4 = getString(R.string.lynx_fw_instructions_firmware_version, new Object[] { uSBAccessibleLynxModule.getFinishedFirmwareVersionString() });
      if (uSBAccessibleLynxModule.getSerialNumber().isEmbedded()) {
        StringBuilder stringBuilder = new StringBuilder();
        stringBuilder.append(str3);
        stringBuilder.append("\n");
        stringBuilder.append(str4);
        str2 = stringBuilder.toString();
      } else {
        StringBuilder stringBuilder = new StringBuilder();
        stringBuilder.append(str3);
        stringBuilder.append("\n");
        stringBuilder.append(str2);
        stringBuilder.append("\n");
        stringBuilder.append(str4);
        str2 = stringBuilder.toString();
      } 
      View view = LayoutInflater.from((Context)this).inflate(17367044, null);
      TextView textView4 = (TextView)view.findViewById(16908308);
      TextView textView5 = (TextView)view.findViewById(16908309);
      textView4.setText(str1);
      textView4.setTextSize(18.0F);
      textView5.setText(str2);
      linearLayout.addView(view);
    } 
    button.setEnabled(this.enableUpdateButton);
  }
  
  protected void onStop() {
    super.onStop();
    AppUtil.getInstance().dismissProgress(UILocation.BOTH);
  }
  
  public void onUpdateLynxFirmwareClicked(View paramView) {
    this.enableUpdateButton = false;
    paramView.setEnabled(false);
    ThreadPool.getDefault().execute(new Runnable() {
          public void run() {
            Iterator<USBAccessibleLynxModule> iterator = FtcLynxFirmwareUpdateActivity.this.modulesToUpdate.iterator();
            while (true) {
              if (iterator.hasNext()) {
                String str;
                USBAccessibleLynxModule uSBAccessibleLynxModule = iterator.next();
                if (FtcLynxFirmwareUpdateActivity.this.cancelUpdate)
                  break; 
                FtcLynxFirmwareUpdateActivity.this.availableFWUpdateResps.clear();
                RobotLog.vv("FtcLynxFirmwareUpdateActivity", "updating %s with %s", new Object[] { uSBAccessibleLynxModule.getSerialNumber(), this.this$0.firmwareImageFile.getName() });
                RobotCoreCommandList.LynxFirmwareUpdate lynxFirmwareUpdate = new RobotCoreCommandList.LynxFirmwareUpdate();
                lynxFirmwareUpdate.serialNumber = uSBAccessibleLynxModule.getSerialNumber();
                lynxFirmwareUpdate.firmwareImageFile = FtcLynxFirmwareUpdateActivity.this.firmwareImageFile;
                lynxFirmwareUpdate.originatorId = FtcLynxFirmwareUpdateActivity.this.originatorId;
                FtcLynxFirmwareUpdateActivity.this.sendOrInject(new Command("CMD_LYNX_FIRMWARE_UPDATE", SimpleGson.getInstance().toJson(lynxFirmwareUpdate)));
                MutableReference<FtcLynxFirmwareUpdateActivity.FwResponseStatus> mutableReference = new MutableReference(FtcLynxFirmwareUpdateActivity.FwResponseStatus.Succeeded);
                FtcLynxFirmwareUpdateActivity ftcLynxFirmwareUpdateActivity = FtcLynxFirmwareUpdateActivity.this;
                RobotCoreCommandList.LynxFirmwareUpdateResp lynxFirmwareUpdateResp = ftcLynxFirmwareUpdateActivity.<RobotCoreCommandList.LynxFirmwareUpdateResp>awaitResponse(ftcLynxFirmwareUpdateActivity.availableFWUpdateResps, (RobotCoreCommandList.LynxFirmwareUpdateResp)null, FlashLoaderManager.secondsFirmwareUpdateTimeout, TimeUnit.SECONDS, mutableReference);
                if (uSBAccessibleLynxModule.getSerialNumber().isEmbedded()) {
                  str = AppUtil.getDefContext().getString(R.string.controlHubDisplayName);
                } else {
                  StringBuilder stringBuilder = new StringBuilder();
                  stringBuilder.append(AppUtil.getDefContext().getString(R.string.expansionHubDisplayName));
                  stringBuilder.append(" ");
                  stringBuilder.append(str.getSerialNumber());
                  str = stringBuilder.toString();
                } 
                if (lynxFirmwareUpdateResp != null && lynxFirmwareUpdateResp.success) {
                  str = FtcLynxFirmwareUpdateActivity.this.getString(R.string.toastLynxFirmwareUpdateSuccessful, new Object[] { str });
                  RobotLog.vv("FtcLynxFirmwareUpdateActivity", "%s", new Object[] { str });
                  AppUtil.getInstance().showToast(UILocation.BOTH, str);
                  continue;
                } 
                if (mutableReference.getValue() != FtcLynxFirmwareUpdateActivity.FwResponseStatus.Cancelled) {
                  if (lynxFirmwareUpdateResp == null) {
                    str = FtcLynxFirmwareUpdateActivity.this.getString(R.string.alertLynxFirmwareUpdateTimedout, new Object[] { str });
                  } else {
                    String str1 = lynxFirmwareUpdateResp.errorMessage;
                    if (str1 != null && !str1.isEmpty()) {
                      str = FtcLynxFirmwareUpdateActivity.this.getString(R.string.alertLynxFirmwareUpdateFailedWithReason, new Object[] { str, str1 });
                    } else {
                      str = FtcLynxFirmwareUpdateActivity.this.getString(R.string.alertLynxFirmwareUpdateFailed, new Object[] { str });
                    } 
                  } 
                  RobotLog.ee("FtcLynxFirmwareUpdateActivity", "%s", new Object[] { str });
                  AppUtil.DialogContext dialogContext = AppUtil.getInstance().showAlertDialog(UILocation.BOTH, FtcLynxFirmwareUpdateActivity.this.getString(R.string.alertLynxFirmwareUpdateFailedTitle), str);
                  try {
                    dialogContext.dismissed.await();
                    break;
                  } catch (InterruptedException interruptedException) {
                    Thread.currentThread().interrupt();
                  } 
                } else {
                  continue;
                } 
              } else {
                break;
              } 
              FtcLynxFirmwareUpdateActivity.this.finish();
              return;
            } 
            FtcLynxFirmwareUpdateActivity.this.finish();
          }
        });
  }
  
  protected void sendOrInject(Command paramCommand) {
    if (this.remoteConfigure) {
      NetworkConnectionHandler.getInstance().sendCommand(paramCommand);
      return;
    } 
    NetworkConnectionHandler.getInstance().injectReceivedCommand(paramCommand);
  }
  
  protected enum FwResponseStatus {
    Cancelled, Succeeded, TimedOut;
    
    static {
      FwResponseStatus fwResponseStatus = new FwResponseStatus("Cancelled", 2);
      Cancelled = fwResponseStatus;
      $VALUES = new FwResponseStatus[] { Succeeded, TimedOut, fwResponseStatus };
    }
  }
  
  protected class ReceiveLoopCallback extends RecvLoopRunnable.DegenerateCallback {
    final String originatorId;
    
    public ReceiveLoopCallback(String param1String) {
      this.originatorId = param1String;
    }
    
    public CallbackResult commandEvent(Command param1Command) throws RobotCoreException {
      // Byte code:
      //   0: aload_1
      //   1: invokevirtual getName : ()Ljava/lang/String;
      //   4: astore_3
      //   5: aload_3
      //   6: invokevirtual hashCode : ()I
      //   9: istore_2
      //   10: iload_2
      //   11: ldc -60637871
      //   13: if_icmpeq -> 59
      //   16: iload_2
      //   17: ldc 349178181
      //   19: if_icmpeq -> 45
      //   22: iload_2
      //   23: ldc 1474679152
      //   25: if_icmpeq -> 31
      //   28: goto -> 73
      //   31: aload_3
      //   32: ldc 'CMD_GET_USB_ACCESSIBLE_LYNX_MODULES_RESP'
      //   34: invokevirtual equals : (Ljava/lang/Object;)Z
      //   37: ifeq -> 73
      //   40: iconst_0
      //   41: istore_2
      //   42: goto -> 75
      //   45: aload_3
      //   46: ldc 'CMD_LYNX_FIRMWARE_UPDATE_RESP'
      //   48: invokevirtual equals : (Ljava/lang/Object;)Z
      //   51: ifeq -> 73
      //   54: iconst_2
      //   55: istore_2
      //   56: goto -> 75
      //   59: aload_3
      //   60: ldc 'CMD_GET_CANDIDATE_LYNX_FIRMWARE_IMAGES_RESP'
      //   62: invokevirtual equals : (Ljava/lang/Object;)Z
      //   65: ifeq -> 73
      //   68: iconst_1
      //   69: istore_2
      //   70: goto -> 75
      //   73: iconst_m1
      //   74: istore_2
      //   75: iload_2
      //   76: ifeq -> 174
      //   79: iload_2
      //   80: iconst_1
      //   81: if_icmpeq -> 148
      //   84: iload_2
      //   85: iconst_2
      //   86: if_icmpeq -> 92
      //   89: goto -> 124
      //   92: aload_1
      //   93: invokevirtual getExtra : ()Ljava/lang/String;
      //   96: invokestatic deserialize : (Ljava/lang/String;)Lorg/firstinspires/ftc/robotcore/internal/network/RobotCoreCommandList$LynxFirmwareUpdateResp;
      //   99: astore_3
      //   100: aload_3
      //   101: getfield originatorId : Ljava/lang/String;
      //   104: ifnull -> 130
      //   107: aload_3
      //   108: getfield originatorId : Ljava/lang/String;
      //   111: aload_0
      //   112: getfield originatorId : Ljava/lang/String;
      //   115: invokevirtual equals : (Ljava/lang/Object;)Z
      //   118: ifeq -> 124
      //   121: goto -> 130
      //   124: aload_0
      //   125: aload_1
      //   126: invokespecial commandEvent : (Lcom/qualcomm/robotcore/robocol/Command;)Lorg/firstinspires/ftc/robotcore/internal/network/CallbackResult;
      //   129: areturn
      //   130: aload_0
      //   131: getfield this$0 : Lcom/qualcomm/ftccommon/FtcLynxFirmwareUpdateActivity;
      //   134: getfield availableFWUpdateResps : Ljava/util/concurrent/BlockingQueue;
      //   137: aload_3
      //   138: invokeinterface offer : (Ljava/lang/Object;)Z
      //   143: pop
      //   144: getstatic org/firstinspires/ftc/robotcore/internal/network/CallbackResult.HANDLED : Lorg/firstinspires/ftc/robotcore/internal/network/CallbackResult;
      //   147: areturn
      //   148: aload_1
      //   149: invokevirtual getExtra : ()Ljava/lang/String;
      //   152: invokestatic deserialize : (Ljava/lang/String;)Lorg/firstinspires/ftc/robotcore/internal/network/RobotCoreCommandList$LynxFirmwareImagesResp;
      //   155: astore_1
      //   156: aload_0
      //   157: getfield this$0 : Lcom/qualcomm/ftccommon/FtcLynxFirmwareUpdateActivity;
      //   160: getfield availableLynxImages : Ljava/util/concurrent/BlockingQueue;
      //   163: aload_1
      //   164: invokeinterface offer : (Ljava/lang/Object;)Z
      //   169: pop
      //   170: getstatic org/firstinspires/ftc/robotcore/internal/network/CallbackResult.HANDLED : Lorg/firstinspires/ftc/robotcore/internal/network/CallbackResult;
      //   173: areturn
      //   174: aload_1
      //   175: invokevirtual getExtra : ()Ljava/lang/String;
      //   178: invokestatic deserialize : (Ljava/lang/String;)Lorg/firstinspires/ftc/robotcore/internal/network/RobotCoreCommandList$USBAccessibleLynxModulesResp;
      //   181: astore_1
      //   182: aload_0
      //   183: getfield this$0 : Lcom/qualcomm/ftccommon/FtcLynxFirmwareUpdateActivity;
      //   186: getfield availableLynxModules : Ljava/util/concurrent/BlockingQueue;
      //   189: aload_1
      //   190: invokeinterface offer : (Ljava/lang/Object;)Z
      //   195: pop
      //   196: getstatic org/firstinspires/ftc/robotcore/internal/network/CallbackResult.HANDLED_CONTINUE : Lorg/firstinspires/ftc/robotcore/internal/network/CallbackResult;
      //   199: areturn
    }
  }
}


/* Location:              C:\Users\Student\Desktop\APK Decompiling\com.qualcomm.ftcdriverstation_38_apps.evozi.com\classes-dex2jar.jar!\com\qualcomm\ftccommon\FtcLynxFirmwareUpdateActivity.class
 * Java compiler version: 6 (50.0)
 * JD-Core Version:       1.1.3
 */